helikopter/__init__.py
helikopter/__main__.py
helikopter/heli_animation.txt
helikopter-1.0.4.dist-info/LICENSE
helikopter-1.0.4.dist-info/METADATA
helikopter-1.0.4.dist-info/WHEEL
helikopter-1.0.4.dist-info/top_level.txt
helikopter-1.0.4.dist-info/RECORD
