Metadata-Version: 2.1
Name: helikopter
Version: 1.0.4
Summary: A simple script to print a helicopter to the terminal
Home-page: https://github.com/wasi-master/helicopter-helicopter
Author: Wasi Master
Author-email: arianmollik323@gmail.com
License: UNKNOWN
Project-URL: Bug Reports, https://github.com/wasi-master/helicopter-helicopter/issues
Project-URL: Say Thanks!, https://saythanks.io/to/wasi-master
Project-URL: Source, https://github.com/wasi-master/helicopter-helicopter
Keywords: helicopter,meme,helikopter,helicopter-helicopter,helikopter-helikopter
Platform: UNKNOWN
Classifier: Development Status :: 5 - Production/Stable
Classifier: Intended Audience :: Developers
Classifier: Topic :: Games/Entertainment
Classifier: Topic :: Terminals
Classifier: License :: OSI Approved :: MIT License
Classifier: Programming Language :: Python :: 3
Classifier: Programming Language :: Python :: 3.0
Classifier: Programming Language :: Python :: 3.1
Classifier: Programming Language :: Python :: 3.2
Classifier: Programming Language :: Python :: 3.3
Classifier: Programming Language :: Python :: 3.4
Classifier: Programming Language :: Python :: 3.5
Classifier: Programming Language :: Python :: 3.6
Classifier: Programming Language :: Python :: 3.7
Classifier: Programming Language :: Python :: 3.8
Classifier: Programming Language :: Python :: 3.9
Classifier: Programming Language :: Python :: 3.10
Classifier: Programming Language :: Python :: 3 :: Only
Requires-Python: >=3.0, <4
License-File: LICENSE
